MANIFEST.in
README.txt
setup.py
docs/HISTORY.txt
silva/__init__.py
silva.pageactions.base.egg-info/PKG-INFO
silva.pageactions.base.egg-info/SOURCES.txt
silva.pageactions.base.egg-info/dependency_links.txt
silva.pageactions.base.egg-info/namespace_packages.txt
silva.pageactions.base.egg-info/not-zip-safe
silva.pageactions.base.egg-info/requires.txt
silva.pageactions.base.egg-info/top_level.txt
silva/pageactions/__init__.py
silva/pageactions/base/__init__.py
silva/pageactions/base/base.py
silva/pageactions/base/configure.zcml
silva/pageactions/base/interfaces.py
silva/pageactions/base/base_templates/pageactions.cpt