Metadata-Version: 1.1
Name: silva.pageactions.base
Version: 1.0
Summary: Generic actions on public pages in Silva CMS
Home-page: https://github.com/silvacms/silva.pageactions.base
Author: Infrae
Author-email: info@infrae.com
License: BSD
Keywords: silva actions pages
Platform: UNKNOWN
Classifier: Framework :: Zope2
Classifier: Programming Language :: Python
Classifier: Topic :: Software Development :: Libraries :: Python Modules
